kecaja/__init__.py
kecaja/command_line.py
kecaja-0.1.dist-info/METADATA
kecaja-0.1.dist-info/WHEEL
kecaja-0.1.dist-info/entry_points.txt
kecaja-0.1.dist-info/top_level.txt
kecaja-0.1.dist-info/RECORD
